odoo/addons/hr_attendance_timer_stop/README.rst
odoo/addons/hr_attendance_timer_stop/__init__.py
odoo/addons/hr_attendance_timer_stop/__manifest__.py
odoo/addons/hr_attendance_timer_stop/models/__init__.py
odoo/addons/hr_attendance_timer_stop/models/hr_attendance.py
odoo/addons/hr_attendance_timer_stop/readme/CONTRIBUTORS.rst
odoo/addons/hr_attendance_timer_stop/readme/DESCRIPTION.rst
odoo/addons/hr_attendance_timer_stop/readme/INSTALL.rst
odoo/addons/hr_attendance_timer_stop/readme/USAGE.rst
odoo/addons/hr_attendance_timer_stop/static/description/index.html
odoo/addons/hr_attendance_timer_stop/tests/__init__.py
odoo/addons/hr_attendance_timer_stop/tests/test_hr_attendance.py
odoo14_addon_hr_attendance_timer_stop-14.0.1.0.3.dist-info/METADATA
odoo14_addon_hr_attendance_timer_stop-14.0.1.0.3.dist-info/WHEEL
odoo14_addon_hr_attendance_timer_stop-14.0.1.0.3.dist-info/top_level.txt
odoo14_addon_hr_attendance_timer_stop-14.0.1.0.3.dist-info/RECORD
