Metadata-Version: 2.1
Name: odoo14-addon-hr_attendance_timer_stop
Version: 14.0.1.0.3
Requires-Python: >=3.6
Requires-Dist: odoo14-addon-project_timesheet_time_control
Requires-Dist: odoo>=14.0a,<14.1dev
Summary: Stops any running timer when an employee checks out in the attendance module.
Home-page: https://git.coopdevs.org/coopdevs/odoo/odoo-addons/hr-attendance-timer-stop
License: AGPL-3
Author: Coopdevs Treball SCCL
Classifier: Programming Language :: Python
Classifier: Framework :: Odoo
Classifier: Framework :: Odoo :: 14.0
Classifier: License :: OSI Approved :: GNU Affero General Public License v3
